src/BCDtoSSeg.v
module BCDtoSSeg (
    input [3:0] BCD, 
    input [3:0] s,
    output reg [0:6] SSeg, 
    output [3:0] an
  );
  
  assign an = BCD;

  always @ ( * ) begin
    case (BCD)
      4'b0000: SSeg = 7'b0000001; // "0"  
  	  4'b0001: SSeg = 7'b1001111; // "1" 
  	  4'b0010: SSeg = 7'b0010010; // "2" 
  	  4'b0011: SSeg = 7'b0000110; // "3" 
  	  4'b0100: SSeg = 7'b1001100; // "4" 
  	  4'b0101: SSeg = 7'b0100100; // "5" 
  	  4'b0110: SSeg = 7'b0100000; // "6" 
  	  4'b0111: SSeg = 7'b0001111; // "7" 
  	  4'b1000: SSeg = 7'b0000000; // "8"  
  	  4'b1001: SSeg = 7'b0000100; // "9" 
      4'ha: SSeg = 7'b0001000;  
      4'hb: SSeg = 7'b1100000;
      4'hc: SSeg = 7'b0110001;
      4'hd: SSeg = 7'b1000010;
      4'he: SSeg = 7'b0110000;
      4'hf: SSeg = 7'b0111000;
       default: SSeg = 7'b0000000;
    endcase
  end

endmodule

src/BCD.v
module separar_num (
    input  [5:0] num,
    input clk2,
    output reg [3:0] BCD
);

parameter cont = 1;
reg algo = 0; // Alterna entre las cifras


always @ ( posedge clk2 ) begin
    case (algo)
    0: begin
        BCD <= num%10; algo = 1; // Se usa "<=" ya que es lógica secuencial
        end
    1: begin
        BCD <= (num- num % 10) / 10; algo=0;
        end
endcase
end
endmodule

src/caja.v
module caja (
    input [5:0] num,
    input clk2,
    input [3:0] s,
    output [0:6] SSeg,
    output [3:0] an
);

  wire [3:0] BCD;

  // Instancia de módulo que separa el número en dígitos
  separar_num suma (
    .num(num),
    .clk2(clk2),
    .BCD(BCD)
  );

  // Instancia del decodificador BCD a 7 segmentos
  BCDtoSSeg sumar (
    .BCD(BCD),
    .s(s),          // señal para multiplexación externa
    .SSeg(SSeg),
    .an(an)
  );

endmodule

src/caja_tb.v
`timescale 1ns/1ps

`include "src/caja.v"
`include "src/BCD.v"
`include "src/BCDtoSSeg.v"

module caja_tb;

  // Entradas
  reg [5:0] num_tb;
  reg clk2_tb;
  reg [3:0] s_tb;  // señal para los ánodos

  // Salidas
  wire [0:6] SSeg_tb;
  wire [3:0] an_tb;

  // Instancia del módulo bajo prueba
  caja uut (
    .num(num_tb),
    .clk2(clk2_tb),
    .s(s_tb),
    .SSeg(SSeg_tb),
    .an(an_tb)
  );

  // Generación del reloj: período 10ns (100MHz)
  always #5 clk2_tb = ~clk2_tb;

  // Multiplexor de ánodos: va activando cada uno cada 40ns
  initial begin
    s_tb = 4'b1110;
    forever begin
      #40 s_tb = {s_tb[2:0], s_tb[3]}; // Rotación circular
    end
  end

  // Estímulos
  initial begin
    clk2_tb = 0;
    num_tb = 0;     #100;
    num_tb = 17;    #100;
    num_tb = 35;    #100;
    num_tb = 42;    #100;
    num_tb = 59;    #100;
    num_tb = 6'd12; #100;
    $finish;
  end

  // Archivo VCD para GTKWave
  initial begin
    $dumpfile("caja_tb.vcd");
    $dumpvars(-1, uut);
  end

endmodule

build/caja_tb.vcd
$date
	Thu Jun 26 20:15:05 2025
$end
$version
	Icarus Verilog
$end
$timescale
	1ps
$end
$scope module caja_tb $end
$scope module uut $end
$var wire 1 ! clk2 $end
$var wire 6 " num [5:0] $end
$var wire 4 # s [3:0] $end
$var wire 4 $ an [3:0] $end
$var wire 7 % SSeg [0:6] $end
$var wire 4 & BCD [3:0] $end
$scope module suma $end
$var wire 1 ! clk2 $end
$var wire 6 ' num [5:0] $end
$var parameter 32 ( cont $end
$var reg 4 ) BCD [3:0] $end
$var reg 1 * algo $end
$upscope $end
$scope module sumar $end
$var wire 4 + BCD [3:0] $end
$var wire 4 , an [3:0] $end
$var wire 4 - s [3:0] $end
$var reg 7 . SSeg [0:6] $end
$upscope $end
$upscope $end
$upscope $end
$enddefinitions $end
$comment Show the parameter values. $end
$dumpall
b1 (
$end
#0
$dumpvars
bx .
b1110 -
bx ,
bx +
0*
bx )
b0 '
bx &
bx %
bx $
b1110 #
b0 "
0!
$end
#5000
b1 %
b1 .
b0 $
b0 ,
b0 &
b0 )
b0 +
1*
1!
#10000
0!
#15000
0*
1!
#20000
0!
#25000
1*
1!
#30000
0!
#35000
0*
1!
#40000
0!
b1101 #
b1101 -
#45000
1*
1!
#50000
0!
#55000
0*
1!
#60000
0!
#65000
1*
1!
#70000
0!
#75000
0*
1!
#80000
0!
b1011 #
b1011 -
#85000
1*
1!
#90000
0!
#95000
0*
1!
#100000
0!
b10001 "
b10001 '
#105000
b1111 %
b1111 .
b111 $
b111 ,
b111 &
b111 )
b111 +
1*
1!
#110000
0!
#115000
b1001111 %
b1001111 .
b1 $
b1 ,
b1 &
b1 )
b1 +
0*
1!
#120000
0!
b111 #
b111 -
#125000
b1111 %
b1111 .
b111 $
b111 ,
b111 &
b111 )
b111 +
1*
1!
#130000
0!
#135000
b1001111 %
b1001111 .
b1 $
b1 ,
b1 &
b1 )
b1 +
0*
1!
#140000
0!
#145000
b1111 %
b1111 .
b111 $
b111 ,
b111 &
b111 )
b111 +
1*
1!
#150000
0!
#155000
b1001111 %
b1001111 .
b1 $
b1 ,
b1 &
b1 )
b1 +
0*
1!
#160000
0!
b1110 #
b1110 -
#165000
b1111 %
b1111 .
b111 $
b111 ,
b111 &
b111 )
b111 +
1*
1!
#170000
0!
#175000
b1001111 %
b1001111 .
b1 $
b1 ,
b1 &
b1 )
b1 +
0*
1!
#180000
0!
#185000
b1111 %
b1111 .
b111 $
b111 ,
b111 &
b111 )
b111 +
1*
1!
#190000
0!
#195000
b1001111 %
b1001111 .
b1 $
b1 ,
b1 &
b1 )
b1 +
0*
1!
#200000
0!
b1101 #
b1101 -
b100011 "
b100011 '
#205000
b100100 %
b100100 .
b101 $
b101 ,
b101 &
b101 )
b101 +
1*
1!
#210000
0!
#215000
b110 %
b110 .
b11 $
b11 ,
b11 &
b11 )
b11 +
0*
1!
#220000
0!
#225000
b100100 %
b100100 .
b101 $
b101 ,
b101 &
b101 )
b101 +
1*
1!
#230000
0!
#235000
b110 %
b110 .
b11 $
b11 ,
b11 &
b11 )
b11 +
0*
1!
#240000
0!
b1011 #
b1011 -
#245000
b100100 %
b100100 .
b101 $
b101 ,
b101 &
b101 )
b101 +
1*
1!
#250000
0!
#255000
b110 %
b110 .
b11 $
b11 ,
b11 &
b11 )
b11 +
0*
1!
#260000
0!
#265000
b100100 %
b100100 .
b101 $
b101 ,
b101 &
b101 )
b101 +
1*
1!
#270000
0!
#275000
b110 %
b110 .
b11 $
b11 ,
b11 &
b11 )
b11 +
0*
1!
#280000
0!
b111 #
b111 -
#285000
b100100 %
b100100 .
b101 $
b101 ,
b101 &
b101 )
b101 +
1*
1!
#290000
0!
#295000
b110 %
b110 .
b11 $
b11 ,
b11 &
b11 )
b11 +
0*
1!
#300000
0!
b101010 "
b101010 '
#305000
b10010 %
b10010 .
b10 $
b10 ,
b10 &
b10 )
b10 +
1*
1!
#310000
0!
#315000
b1001100 %
b1001100 .
b100 $
b100 ,
b100 &
b100 )
b100 +
0*
1!
#320000
0!
b1110 #
b1110 -
#325000
b10010 %
b10010 .
b10 $
b10 ,
b10 &
b10 )
b10 +
1*
1!
#330000
0!
#335000
b1001100 %
b1001100 .
b100 $
b100 ,
b100 &
b100 )
b100 +
0*
1!
#340000
0!
#345000
b10010 %
b10010 .
b10 $
b10 ,
b10 &
b10 )
b10 +
1*
1!
#350000
0!
#355000
b1001100 %
b1001100 .
b100 $
b100 ,
b100 &
b100 )
b100 +
0*
1!
#360000
0!
b1101 #
b1101 -
#365000
b10010 %
b10010 .
b10 $
b10 ,
b10 &
b10 )
b10 +
1*
1!
#370000
0!
#375000
b1001100 %
b1001100 .
b100 $
b100 ,
b100 &
b100 )
b100 +
0*
1!
#380000
0!
#385000
b10010 %
b10010 .
b10 $
b10 ,
b10 &
b10 )
b10 +
1*
1!
#390000
0!
#395000
b1001100 %
b1001100 .
b100 $
b100 ,
b100 &
b100 )
b100 +
0*
1!
#400000
0!
b1011 #
b1011 -
b111011 "
b111011 '
#405000
b100 %
b100 .
b1001 $
b1001 ,
b1001 &
b1001 )
b1001 +
1*
1!
#410000
0!
#415000
b100100 %
b100100 .
b101 $
b101 ,
b101 &
b101 )
b101 +
0*
1!
#420000
0!
#425000
b100 %
b100 .
b1001 $
b1001 ,
b1001 &
b1001 )
b1001 +
1*
1!
#430000
0!
#435000
b100100 %
b100100 .
b101 $
b101 ,
b101 &
b101 )
b101 +
0*
1!
#440000
0!
b111 #
b111 -
#445000
b100 %
b100 .
b1001 $
b1001 ,
b1001 &
b1001 )
b1001 +
1*
1!
#450000
0!
#455000
b100100 %
b100100 .
b101 $
b101 ,
b101 &
b101 )
b101 +
0*
1!
#460000
0!
#465000
b100 %
b100 .
b1001 $
b1001 ,
b1001 &
b1001 )
b1001 +
1*
1!
#470000
0!
#475000
b100100 %
b100100 .
b101 $
b101 ,
b101 &
b101 )
b101 +
0*
1!
#480000
0!
b1110 #
b1110 -
#485000
b100 %
b100 .
b1001 $
b1001 ,
b1001 &
b1001 )
b1001 +
1*
1!
#490000
0!
#495000
b100100 %
b100100 .
b101 $
b101 ,
b101 &
b101 )
b101 +
0*
1!
#500000
0!
b1100 "
b1100 '
#505000
b10010 %
b10010 .
b10 $
b10 ,
b10 &
b10 )
b10 +
1*
1!
#510000
0!
#515000
b1001111 %
b1001111 .
b1 $
b1 ,
b1 &
b1 )
b1 +
0*
1!
#520000
0!
b1101 #
b1101 -
#525000
b10010 %
b10010 .
b10 $
b10 ,
b10 &
b10 )
b10 +
1*
1!
#530000
0!
#535000
b1001111 %
b1001111 .
b1 $
b1 ,
b1 &
b1 )
b1 +
0*
1!
#540000
0!
#545000
b10010 %
b10010 .
b10 $
b10 ,
b10 &
b10 )
b10 +
1*
1!
#550000
0!
#555000
b1001111 %
b1001111 .
b1 $
b1 ,
b1 &
b1 )
b1 +
0*
1!
#560000
0!
b1011 #
b1011 -
#565000
b10010 %
b10010 .
b10 $
b10 ,
b10 &
b10 )
b10 +
1*
1!
#570000
0!
#575000
b1001111 %
b1001111 .
b1 $
b1 ,
b1 &
b1 )
b1 +
0*
1!
#580000
0!
#585000
b10010 %
b10010 .
b10 $
b10 ,
b10 &
b10 )
b10 +
1*
1!
#590000
0!
#595000
b1001111 %
b1001111 .
b1 $
b1 ,
b1 &
b1 )
b1 +
0*
1!
#600000
0!
b111 #
b111 -
