src/BCD.v
module separar_num (
    input  [5:0] num,
    input clk2,
    output reg [3:0] BCD
);

parameter cont = 1;
reg algo = 0; // Alterna entre las cifras


always @ ( posedge clk2 ) begin
    case (algo)
    0: begin
        BCD <= num%10; algo = 1; // Se usa "<=" ya que es lógica secuencial
        end
    1: begin
        BCD <= (num- num % 10) / 10; algo=0;
        end
endcase
end
endmodule

src/BCD_tb.v
`timescale 1ns/1ps
`include "src/BCD.v"  
module separar_num_tb;

  // Entradas
  reg [5:0] num_tb;
  reg clk2_tb;

  // Salidas
  wire [3:0] BCD_t;

  // Instancia del módulo bajo prueba
  separar_num uut (
    .num(num_tb),
    .clk2(clk2_tb),
    .BCD(BCD_t)
  );

  // Generación del reloj: período 10ns (100MHz)
  always #5 clk2_tb = ~clk2_tb;

  // Estímulos
  initial begin
    clk2_tb = 0;
    num_tb = 0;     #100;
    num_tb = 17;    #100;
    num_tb = 35;    #100;
    num_tb = 42;    #100;
    num_tb = 59;    #100;
    num_tb = 6'd12; #100;
    $finish;
  end

  // Archivo VCD para GTKWave
  initial begin
    $dumpfile("separar_num_tb.vcd");
    $dumpvars(-1, uut);
  end

endmodule

build/separar_num_tb.vcd
$date
	Sun Jun 22 15:45:05 2025
$end
$version
	Icarus Verilog
$end
$timescale
	1ps
$end
$scope module separar_num_tb $end
$scope module uut $end
$var wire 1 ! clk2 $end
$var wire 6 " num [5:0] $end
$var parameter 32 # cont $end
$var reg 4 $ BCD [3:0] $end
$var reg 1 % algo $end
$upscope $end
$upscope $end
$enddefinitions $end
$comment Show the parameter values. $end
$dumpall
b1 #
$end
#0
$dumpvars
0%
bx $
b0 "
0!
$end
#5000
b0 $
1%
1!
#10000
0!
#15000
0%
1!
#20000
0!
#25000
1%
1!
#30000
0!
#35000
0%
1!
#40000
0!
#45000
1%
1!
#50000
0!
#55000
0%
1!
#60000
0!
#65000
1%
1!
#70000
0!
#75000
0%
1!
#80000
0!
#85000
1%
1!
#90000
0!
#95000
0%
1!
#100000
0!
b10001 "
#105000
b111 $
1%
1!
#110000
0!
#115000
b1 $
0%
1!
#120000
0!
#125000
b111 $
1%
1!
#130000
0!
#135000
b1 $
0%
1!
#140000
0!
#145000
b111 $
1%
1!
#150000
0!
#155000
b1 $
0%
1!
#160000
0!
#165000
b111 $
1%
1!
#170000
0!
#175000
b1 $
0%
1!
#180000
0!
#185000
b111 $
1%
1!
#190000
0!
#195000
b1 $
0%
1!
#200000
0!
b100011 "
#205000
b101 $
1%
1!
#210000
0!
#215000
b11 $
0%
1!
#220000
0!
#225000
b101 $
1%
1!
#230000
0!
#235000
b11 $
0%
1!
#240000
0!
#245000
b101 $
1%
1!
#250000
0!
#255000
b11 $
0%
1!
#260000
0!
#265000
b101 $
1%
1!
#270000
0!
#275000
b11 $
0%
1!
#280000
0!
#285000
b101 $
1%
1!
#290000
0!
#295000
b11 $
0%
1!
#300000
0!
b101010 "
#305000
b10 $
1%
1!
#310000
0!
#315000
b100 $
0%
1!
#320000
0!
#325000
b10 $
1%
1!
#330000
0!
#335000
b100 $
0%
1!
#340000
0!
#345000
b10 $
1%
1!
#350000
0!
#355000
b100 $
0%
1!
#360000
0!
#365000
b10 $
1%
1!
#370000
0!
#375000
b100 $
0%
1!
#380000
0!
#385000
b10 $
1%
1!
#390000
0!
#395000
b100 $
0%
1!
#400000
0!
b111011 "
#405000
b1001 $
1%
1!
#410000
0!
#415000
b101 $
0%
1!
#420000
0!
#425000
b1001 $
1%
1!
#430000
0!
#435000
b101 $
0%
1!
#440000
0!
#445000
b1001 $
1%
1!
#450000
0!
#455000
b101 $
0%
1!
#460000
0!
#465000
b1001 $
1%
1!
#470000
0!
#475000
b101 $
0%
1!
#480000
0!
#485000
b1001 $
1%
1!
#490000
0!
#495000
b101 $
0%
1!
#500000
0!
b1100 "
#505000
b10 $
1%
1!
#510000
0!
#515000
b1 $
0%
1!
#520000
0!
#525000
b10 $
1%
1!
#530000
0!
#535000
b1 $
0%
1!
#540000
0!
#545000
b10 $
1%
1!
#550000
0!
#555000
b1 $
0%
1!
#560000
0!
#565000
b10 $
1%
1!
#570000
0!
#575000
b1 $
0%
1!
#580000
0!
#585000
b10 $
1%
1!
#590000
0!
#595000
b1 $
0%
1!
