src/simon.v
// SPDX-FileCopyrightText: © 2022 Uri Shaked <uri@wokwi.com>
// SPDX-License-Identifier: MIT

/*
 * Simon Says game in Verilog. Wokwi Simulation project:
 * https://wokwi.com/projects/352319274216569857
 */

`default_nettype none

module SimonTop (
    input wire CLOCK_50,
    input wire [3:0] KEY,
    output wire [9:0] LEDR,
    output wire BUZZER
);

  wire [3:0] leds;
  wire sound;

  simon simon_game (
      .clk   (CLOCK_50),
      .rst   (~KEY[0]),                // Reset con KEY[0], activo bajo
      .ticks_per_milli (16'd50000),   // 50 MHz -> 50000 ticks por milisegundo
      .btn   (~KEY[3:0]),              // Botones activos bajos
      .led   (leds),
      .sound (sound)
  );

  assign LEDR[3:0] = leds;
  assign LEDR[9:4] = 6'b000000; // LEDs extra apagados
  assign BUZZER = sound;

endmodule

module play (
    input wire clk,
    input wire rst,
    input wire [15:0] ticks_per_milli,
    input wire [9:0] freq,
    output reg sound
);
  reg [31:0] tick_counter;
  wire [31:0] ticks_per_second = ticks_per_milli * 1000;

  always @(posedge clk) begin
    if (rst) begin
      tick_counter <= 0;
      sound <= 0;
    end else if (freq == 0) begin
      sound <= 0;
    end else begin
      tick_counter <= tick_counter + freq;
      if (tick_counter >= (ticks_per_second >> 1)) begin
        sound <= !sound;
        tick_counter <= tick_counter + freq - (ticks_per_second >> 1);
      end
    end
  end

endmodule

module simon (
    input wire clk,
    input wire rst,
    input wire [15:0] ticks_per_milli,
    input wire [3:0] btn,
    output reg [3:0] led,
    output wire sound
);

  localparam MAX_GAME_LEN = 32;

  wire [9:0] GAME_TONES[3:0];
  assign GAME_TONES[0] = 196;  // G3
  assign GAME_TONES[1] = 262;  // C4
  assign GAME_TONES[2] = 330;  // E4
  assign GAME_TONES[3] = 784;  // G5

  wire [9:0] SUCCESS_TONES[6:0];
  assign SUCCESS_TONES[0] = 330;  // E4
  assign SUCCESS_TONES[1] = 392;  // G4
  assign SUCCESS_TONES[2] = 659;  // E5
  assign SUCCESS_TONES[3] = 523;  // C5
  assign SUCCESS_TONES[4] = 587;  // D5
  assign SUCCESS_TONES[5] = 784;  // G5
  assign SUCCESS_TONES[6] = 0;  // silence

  wire [9:0] GAMEOVER_TONES[3:0];
  assign GAMEOVER_TONES[0] = 622;  // D#5 
  assign GAMEOVER_TONES[1] = 587;  // D5
  assign GAMEOVER_TONES[2] = 554;  // C#5
  assign GAMEOVER_TONES[3] = 523;  // C5

  localparam StatePowerOn = 0;
  localparam StateInit = 1;
  localparam StatePlay = 2;
  localparam StatePlayWait = 3;
  localparam StateUserWait = 4;
  localparam StateUserInput = 5;
  localparam StateNextLevel = 6;
  localparam StateGameOver = 7;

  reg [4:0] seq_counter;
  reg [4:0] seq_length;
  reg [1:0] seq[MAX_GAME_LEN-1:0];
  reg [2:0] state;

  reg [15:0] tick_counter;
  reg [9:0] millis_counter;
  reg [2:0] tone_sequence_counter;
  reg [9:0] sound_freq;

  reg [1:0] next_random;
  reg [1:0] user_input;

  play play1 (
      .clk(clk),
      .rst(rst),
      .ticks_per_milli(ticks_per_milli),
      .freq(sound_freq),
      .sound(sound)
  );

  always @(posedge clk) begin
    if (rst) begin
      seq_length <= 0;
      seq_counter <= 0;
      tick_counter <= 0;
      millis_counter <= 0;
      sound_freq <= 0;
      next_random <= 0;
      state <= StatePowerOn;
      seq[0] <= 0;
      led <= 4'b0000;
    end else begin
      tick_counter <= tick_counter + 1;
      next_random  <= next_random + 1;

      if (tick_counter == ticks_per_milli) begin
        tick_counter   <= 0;
        millis_counter <= millis_counter + 1;
      end

      case (state)
        StatePowerOn: begin
          led <= 4'b1111;
          led[millis_counter[9:8]] <= 1'b0;
          // Wait until the user presses some button - the delay will seed the random sequence
          if (btn != 0) begin
            state <= StateInit;
            led <= 4'b0000;
            millis_counter <= 0;
          end
        end
        StateInit: begin
          seq[0] <= next_random;
          seq_length <= 1;
          seq_counter <= 0;
          tone_sequence_counter <= 0;
          if (millis_counter == 500) begin
            state <= StatePlay;
          end
        end
        StatePlay: begin
          led <= 0;
          led[seq[seq_counter]] <= 1'b1;
          sound_freq <= GAME_TONES[seq[seq_counter]];
          millis_counter <= 0;
          state <= StatePlayWait;
        end
        StatePlayWait: begin
          if (millis_counter == 300) begin
            led <= 0;
            sound_freq <= 0;
          end
          if (millis_counter == 400) begin
            if (seq_counter + 1 == seq_length) begin
              state <= StateUserWait;
              millis_counter <= 0;
              seq_counter <= 0;
            end else begin
              seq_counter <= seq_counter + 1;
              state <= StatePlay;
            end
          end
        end
        StateUserWait: begin
          led <= 0;
          millis_counter <= 0;
          if (btn != 0) begin
            state <= StateUserInput;
            case (btn)
              4'b0001: user_input <= 0;
              4'b0010: user_input <= 1;
              4'b0100: user_input <= 2;
              4'b1000: user_input <= 3;
              default: state <= StateUserWait;
            endcase
          end
        end
        StateUserInput: begin
          led <= 0;
          led[user_input] <= 1'b1;
          sound_freq <= GAME_TONES[user_input];
          if (millis_counter == 300) begin
            sound_freq <= 0;
            if (user_input == seq[seq_counter]) begin
              if (seq_counter + 1 == seq_length) begin
                millis_counter <= 0;
                seq[seq_length] <= next_random;
                seq_length <= seq_length + 1;
                state <= StateNextLevel;
              end else begin
                seq_counter <= seq_counter + 1;
                state <= StateUserWait;
              end
            end else begin
              millis_counter <= 0;
              state <= StateGameOver;
            end
          end
        end
        StateNextLevel: begin
          led <= 0;
          if (millis_counter == 150) begin
            if (tone_sequence_counter < 7) begin
              sound_freq <= SUCCESS_TONES[tone_sequence_counter];
            end else begin
              sound_freq <= 0;
              tone_sequence_counter <= 0;
              seq_counter <= 0;
              state <= StatePlay;
            end
            tone_sequence_counter <= tone_sequence_counter + 1;
            millis_counter <= 0;
          end
        end
        StateGameOver: begin
          led <= millis_counter[7] ? 4'b1111 : 4'b0000;

          if (tone_sequence_counter == 4) begin
            // trembling sound
            sound_freq <= GAMEOVER_TONES[3] - 16 + millis_counter[4:0];
            if (millis_counter == 1000) begin
              tone_sequence_counter <= 7;
              sound_freq <= 0;
            end
          end else if (millis_counter == 300) begin
            if (tone_sequence_counter < 4) begin
              sound_freq <= GAMEOVER_TONES[tone_sequence_counter[1:0]];
              tone_sequence_counter <= tone_sequence_counter + 1;
            end
            millis_counter <= 0;
          end

          if (btn != 0) begin
            led <= 4'b0000;
            sound_freq <= 0;
            millis_counter <= 0;
            state <= StateInit;
          end
        end
      endcase
    end
  end

endmodule

src/simon_tb.v
`timescale 1ns/1ps
`include "src/simon.v"  

module simon_tb;

  // Entradas
  reg clk;
  reg rst;
  reg [3:0] btn;

  // Salidas
  wire [3:0] led;
  wire sound;

  // Parámetro de simulación
  wire [15:0] ticks_per_milli = 16'd50; // Simulación rápida

  // Instancia del módulo simon
  simon dut (
    .clk(clk),
    .rst(rst),
    .ticks_per_milli(ticks_per_milli),
    .btn(btn),
    .led(led),
    .sound(sound)
  );

  // Generación de reloj
  always #10 clk = ~clk;

  // Simulación
  initial begin
    // Inicialización
    clk = 0;
    rst = 1;
    btn = 4'b0000;
    #100;
    rst = 0;

    // Espera un tiempo y presiona un botón para iniciar
    #1000;
    btn = 4'b0001;  // presionar botón 0
    #100;
    btn = 4'b0000;

    // Espera a que el juego reproduzca la secuencia
    #50000;

    // Suponiendo que la primera secuencia es [0] (esto depende del generador interno)
    // Simular respuesta del jugador con botón 0:
    btn = 4'b0001;  #100;
    btn = 4'b0000;  #10000;

    // Esperar avance de nivel
    #100000;

    // Segundo intento (suponiendo nueva secuencia es [0,1])
    btn = 4'b0001;  #100;
    btn = 4'b0000;  #10000;
    btn = 4'b0010;  #100;
    btn = 4'b0000;

    // Fin de prueba
    #200000;
    $finish;
  end

  // Dump para GTKWave
  initial begin
    $dumpfile("simon_tb.vcd");
    $dumpvars(0, simon_tb);
  end

endmodule

build/simon_tb.vcd
$date
	Tue Jul  1 09:24:43 2025
$end
$version
	Icarus Verilog
$end
$timescale
	1ps
$end
$scope module simon_tb $end
$var wire 16 ! ticks_per_milli [15:0] $end
$var wire 1 " sound $end
$var wire 4 # led [3:0] $end
$var reg 4 $ btn [3:0] $end
$var reg 1 % clk $end
$var reg 1 & rst $end
$scope module dut $end
$var wire 4 ' btn [3:0] $end
$var wire 1 % clk $end
$var wire 1 & rst $end
$var wire 16 ( ticks_per_milli [15:0] $end
$var wire 1 " sound $end
$var parameter 32 ) MAX_GAME_LEN $end
$var parameter 32 * StateGameOver $end
$var parameter 32 + StateInit $end
$var parameter 32 , StateNextLevel $end
$var parameter 32 - StatePlay $end
$var parameter 32 . StatePlayWait $end
$var parameter 32 / StatePowerOn $end
$var parameter 32 0 StateUserInput $end
$var parameter 32 1 StateUserWait $end
$var reg 4 2 led [3:0] $end
$var reg 10 3 millis_counter [9:0] $end
$var reg 2 4 next_random [1:0] $end
$var reg 5 5 seq_counter [4:0] $end
$var reg 5 6 seq_length [4:0] $end
$var reg 10 7 sound_freq [9:0] $end
$var reg 3 8 state [2:0] $end
$var reg 16 9 tick_counter [15:0] $end
$var reg 3 : tone_sequence_counter [2:0] $end
$var reg 2 ; user_input [1:0] $end
$scope module play1 $end
$var wire 1 % clk $end
$var wire 10 < freq [9:0] $end
$var wire 1 & rst $end
$var wire 16 = ticks_per_milli [15:0] $end
$var wire 32 > ticks_per_second [31:0] $end
$var reg 1 " sound $end
$var reg 32 ? tick_counter [31:0] $end
$upscope $end
$upscope $end
$upscope $end
$enddefinitions $end
$comment Show the parameter values. $end
$dumpall
b100 1
b101 0
b0 /
b11 .
b10 -
b110 ,
b1 +
b111 *
b100000 )
$end
#0
$dumpvars
bx ?
b1100001101010000 >
b110010 =
bx <
bx ;
bx :
bx 9
bx 8
bx 7
bx 6
bx 5
bx 4
bx 3
bx 2
b110010 (
b0 '
1&
0%
b0 $
bx #
x"
b110010 !
$end
#10000
0"
b0 ?
b0 #
b0 2
b0 8
b0 4
b0 7
b0 <
b0 3
b0 9
b0 5
b0 6
1%
#20000
0%
#30000
1%
#40000
0%
#50000
1%
#60000
0%
#70000
1%
#80000
0%
#90000
1%
#100000
0%
0&
#110000
b1110 #
b1110 2
b1 4
b1 9
1%
#120000
0%
#130000
b1110 #
b1110 2
b10 4
b10 9
1%
#140000
0%
#150000
b1110 #
b1110 2
b11 4
b11 9
1%
#160000
0%
#170000
b1110 #
b1110 2
b0 4
b100 9
1%
#180000
0%
#190000
b1110 #
b1110 2
b1 4
b101 9
1%
#200000
0%
#210000
b1110 #
b1110 2
b10 4
b110 9
1%
#220000
0%
#230000
b1110 #
b1110 2
b11 4
b111 9
1%
#240000
0%
#250000
b1110 #
b1110 2
b0 4
b1000 9
1%
#260000
0%
#270000
b1110 #
b1110 2
b1 4
b1001 9
1%
#280000
0%
#290000
b1110 #
b1110 2
b10 4
b1010 9
1%
#300000
0%
#310000
b1110 #
b1110 2
b11 4
b1011 9
1%
#320000
0%
#330000
b1110 #
b1110 2
b0 4
b1100 9
1%
#340000
0%
#350000
b1110 #
b1110 2
b1 4
b1101 9
1%
#360000
0%
#370000
b1110 #
b1110 2
b10 4
b1110 9
1%
#380000
0%
#390000
b1110 #
b1110 2
b11 4
b1111 9
1%
#400000
0%
#410000
b1110 #
b1110 2
b0 4
b10000 9
1%
#420000
0%
#430000
b1110 #
b1110 2
b1 4
b10001 9
1%
#440000
0%
#450000
b1110 #
b1110 2
b10 4
b10010 9
1%
#460000
0%
#470000
b1110 #
b1110 2
b11 4
b10011 9
1%
#480000
0%
#490000
b1110 #
b1110 2
b0 4
b10100 9
1%
#500000
0%
#510000
b1110 #
b1110 2
b1 4
b10101 9
1%
#520000
0%
#530000
b1110 #
b1110 2
b10 4
b10110 9
1%
#540000
0%
#550000
b1110 #
b1110 2
b11 4
b10111 9
1%
#560000
0%
#570000
b1110 #
b1110 2
b0 4
b11000 9
1%
#580000
0%
#590000
b1110 #
b1110 2
b1 4
b11001 9
1%
#600000
0%
#610000
b1110 #
b1110 2
b10 4
b11010 9
1%
#620000
0%
#630000
b1110 #
b1110 2
b11 4
b11011 9
1%
#640000
0%
#650000
b1110 #
b1110 2
b0 4
b11100 9
1%
#660000
0%
#670000
b1110 #
b1110 2
b1 4
b11101 9
1%
#680000
0%
#690000
b1110 #
b1110 2
b10 4
b11110 9
1%
#700000
0%
#710000
b1110 #
b1110 2
b11 4
b11111 9
1%
#720000
0%
#730000
b1110 #
b1110 2
b0 4
b100000 9
1%
#740000
0%
#750000
b1110 #
b1110 2
b1 4
b100001 9
1%
#760000
0%
#770000
b1110 #
b1110 2
b10 4
b100010 9
1%
#780000
0%
#790000
b1110 #
b1110 2
b11 4
b100011 9
1%
#800000
0%
#810000
b1110 #
b1110 2
b0 4
b100100 9
1%
#820000
0%
#830000
b1110 #
b1110 2
b1 4
b100101 9
1%
#840000
0%
#850000
b1110 #
b1110 2
b10 4
b100110 9
1%
#860000
0%
#870000
b1110 #
b1110 2
b11 4
b100111 9
1%
#880000
0%
#890000
b1110 #
b1110 2
b0 4
b101000 9
1%
#900000
0%
#910000
b1110 #
b1110 2
b1 4
b101001 9
1%
#920000
0%
#930000
b1110 #
b1110 2
b10 4
b101010 9
1%
#940000
0%
#950000
b1110 #
b1110 2
b11 4
b101011 9
1%
#960000
0%
#970000
b1110 #
b1110 2
b0 4
b101100 9
1%
#980000
0%
#990000
b1110 #
b1110 2
b1 4
b101101 9
1%
#1000000
0%
#1010000
b1110 #
b1110 2
b10 4
b101110 9
1%
#1020000
0%
#1030000
b1110 #
b1110 2
b11 4
b101111 9
1%
#1040000
0%
#1050000
b1110 #
b1110 2
b0 4
b110000 9
1%
#1060000
0%
#1070000
b1110 #
b1110 2
b1 4
b110001 9
1%
#1080000
0%
#1090000
b1110 #
b1110 2
b10 4
b110010 9
1%
#1100000
0%
b1 $
b1 '
#1110000
b1 8
b0 #
b0 2
b0 3
b11 4
b0 9
1%
#1120000
0%
#1130000
b0 :
b1 6
b0 4
b1 9
1%
#1140000
0%
#1150000
b1 4
b10 9
1%
#1160000
0%
#1170000
b10 4
b11 9
1%
#1180000
0%
#1190000
b11 4
b100 9
1%
#1200000
0%
b0 $
b0 '
#1210000
b0 4
b101 9
1%
#1220000
0%
#1230000
b1 4
b110 9
1%
#1240000
0%
#1250000
b10 4
b111 9
1%
#1260000
0%
#1270000
b11 4
b1000 9
1%
#1280000
0%
#1290000
b0 4
b1001 9
1%
#1300000
0%
#1310000
b1 4
b1010 9
1%
#1320000
0%
#1330000
b10 4
b1011 9
1%
#1340000
0%
#1350000
b11 4
b1100 9
1%
#1360000
0%
#1370000
b0 4
b1101 9
1%
#1380000
0%
#1390000
b1 4
b1110 9
1%
#1400000
0%
#1410000
b10 4
b1111 9
1%
#1420000
0%
#1430000
b11 4
b10000 9
1%
#1440000
0%
#1450000
b0 4
b10001 9
1%
#1460000
0%
#1470000
b1 4
b10010 9
1%
#1480000
0%
#1490000
b10 4
b10011 9
1%
#1500000
0%
#1510000
b11 4
b10100 9
1%
#1520000
0%
#1530000
b0 4
b10101 9
1%
#1540000
0%
#1550000
b1 4
b10110 9
1%
#1560000
0%
#1570000
b10 4
b10111 9
1%
#1580000
0%
#1590000
b11 4
b11000 9
1%
#1600000
0%
#1610000
b0 4
b11001 9
1%
#1620000
0%
#1630000
b1 4
b11010 9
1%
#1640000
0%
#1650000
b10 4
b11011 9
1%
#1660000
0%
#1670000
b11 4
b11100 9
1%
#1680000
0%
#1690000
b0 4
b11101 9
1%
#1700000
0%
#1710000
b1 4
b11110 9
1%
#1720000
0%
#1730000
b10 4
b11111 9
1%
#1740000
0%
#1750000
b11 4
b100000 9
1%
#1760000
0%
#1770000
b0 4
b100001 9
1%
#1780000
0%
#1790000
b1 4
b100010 9
1%
#1800000
0%
#1810000
b10 4
b100011 9
1%
#1820000
0%
#1830000
b11 4
b100100 9
1%
#1840000
0%
#1850000
b0 4
b100101 9
1%
#1860000
0%
#1870000
b1 4
b100110 9
1%
#1880000
0%
#1890000
b10 4
b100111 9
1%
#1900000
0%
#1910000
b11 4
b101000 9
1%
#1920000
0%
#1930000
b0 4
b101001 9
1%
#1940000
0%
#1950000
b1 4
b101010 9
1%
#1960000
0%
#1970000
b10 4
b101011 9
1%
#1980000
0%
#1990000
b11 4
b101100 9
1%
#2000000
0%
#2010000
b0 4
b101101 9
1%
#2020000
0%
#2030000
b1 4
b101110 9
1%
#2040000
0%
#2050000
b10 4
b101111 9
1%
#2060000
0%
#2070000
b11 4
b110000 9
1%
#2080000
0%
#2090000
b0 4
b110001 9
1%
#2100000
0%
#2110000
b1 4
b110010 9
1%
#2120000
0%
#2130000
b1 3
b10 4
b0 9
1%
#2140000
0%
#2150000
b11 4
b1 9
1%
#2160000
0%
#2170000
b0 4
b10 9
1%
#2180000
0%
#2190000
b1 4
b11 9
1%
#2200000
0%
#2210000
b10 4
b100 9
1%
#2220000
0%
#2230000
b11 4
b101 9
1%
#2240000
0%
#2250000
b0 4
b110 9
1%
#2260000
0%
#2270000
b1 4
b111 9
1%
#2280000
0%
#2290000
b10 4
b1000 9
1%
#2300000
0%
#2310000
b11 4
b1001 9
1%
#2320000
0%
#2330000
b0 4
b1010 9
1%
#2340000
0%
#2350000
b1 4
b1011 9
1%
#2360000
0%
#2370000
b10 4
b1100 9
1%
#2380000
0%
#2390000
b11 4
b1101 9
1%
#2400000
0%
#2410000
b0 4
b1110 9
1%
#2420000
0%
#2430000
b1 4
b1111 9
1%
#2440000
0%
#2450000
b10 4
b10000 9
1%
#2460000
0%
#2470000
b11 4
b10001 9
1%
#2480000
0%
#2490000
b0 4
b10010 9
1%
#2500000
0%
#2510000
b1 4
b10011 9
1%
#2520000
0%
#2530000
b10 4
b10100 9
1%
#2540000
0%
#2550000
b11 4
b10101 9
1%
#2560000
0%
#2570000
b0 4
b10110 9
1%
#2580000
0%
#2590000
b1 4
b10111 9
1%
#2600000
0%
#2610000
b10 4
b11000 9
1%
#2620000
0%
#2630000
b11 4
b11001 9
1%
#2640000
0%
#2650000
b0 4
b11010 9
1%
#2660000
0%
#2670000
b1 4
b11011 9
1%
#2680000
0%
#2690000
b10 4
b11100 9
1%
#2700000
0%
#2710000
b11 4
b11101 9
1%
#2720000
0%
#2730000
b0 4
b11110 9
1%
#2740000
0%
#2750000
b1 4
b11111 9
1%
#2760000
0%
#2770000
b10 4
b100000 9
1%
#2780000
0%
#2790000
b11 4
b100001 9
1%
#2800000
0%
#2810000
b0 4
b100010 9
1%
#2820000
0%
#2830000
b1 4
b100011 9
1%
#2840000
0%
#2850000
b10 4
b100100 9
1%
#2860000
0%
#2870000
b11 4
b100101 9
1%
#2880000
0%
#2890000
b0 4
b100110 9
1%
#2900000
0%
#2910000
b1 4
b100111 9
1%
#2920000
0%
#2930000
b10 4
b101000 9
1%
#2940000
0%
#2950000
b11 4
b101001 9
1%
#2960000
0%
#2970000
b0 4
b101010 9
1%
#2980000
0%
#2990000
b1 4
b101011 9
1%
#3000000
0%
#3010000
b10 4
b101100 9
1%
#3020000
0%
#3030000
b11 4
b101101 9
1%
#3040000
0%
#3050000
b0 4
b101110 9
1%
#3060000
0%
#3070000
b1 4
b101111 9
1%
#3080000
0%
#3090000
b10 4
b110000 9
1%
#3100000
0%
#3110000
b11 4
b110001 9
1%
#3120000
0%
#3130000
b0 4
b110010 9
1%
#3140000
0%
#3150000
b10 3
b1 4
b0 9
1%
#3160000
0%
#3170000
b10 4
b1 9
1%
#3180000
0%
#3190000
b11 4
b10 9
1%
#3200000
0%
#3210000
b0 4
b11 9
1%
#3220000
0%
#3230000
b1 4
b100 9
1%
#3240000
0%
#3250000
b10 4
b101 9
1%
#3260000
0%
#3270000
b11 4
b110 9
1%
#3280000
0%
#3290000
b0 4
b111 9
1%
#3300000
0%
#3310000
b1 4
b1000 9
1%
#3320000
0%
#3330000
b10 4
b1001 9
1%
#3340000
0%
#3350000
b11 4
b1010 9
1%
#3360000
0%
#3370000
b0 4
b1011 9
1%
#3380000
0%
#3390000
b1 4
b1100 9
1%
#3400000
0%
#3410000
b10 4
b1101 9
1%
#3420000
0%
#3430000
b11 4
b1110 9
1%
#3440000
0%
#3450000
b0 4
b1111 9
1%
#3460000
0%
#3470000
b1 4
b10000 9
1%
#3480000
0%
#3490000
b10 4
b10001 9
1%
#3500000
0%
#3510000
b11 4
b10010 9
1%
#3520000
0%
#3530000
b0 4
b10011 9
1%
#3540000
0%
#3550000
b1 4
b10100 9
1%
#3560000
0%
#3570000
b10 4
b10101 9
1%
#3580000
0%
#3590000
b11 4
b10110 9
1%
#3600000
0%
#3610000
b0 4
b10111 9
1%
#3620000
0%
#3630000
b1 4
b11000 9
1%
#3640000
0%
#3650000
b10 4
b11001 9
1%
#3660000
0%
#3670000
b11 4
b11010 9
1%
#3680000
0%
#3690000
b0 4
b11011 9
1%
#3700000
0%
#3710000
b1 4
b11100 9
1%
#3720000
0%
#3730000
b10 4
b11101 9
1%
#3740000
0%
#3750000
b11 4
b11110 9
1%
#3760000
0%
#3770000
b0 4
b11111 9
1%
#3780000
0%
#3790000
b1 4
b100000 9
1%
#3800000
0%
#3810000
b10 4
b100001 9
1%
#3820000
0%
#3830000
b11 4
b100010 9
1%
#3840000
0%
#3850000
b0 4
b100011 9
1%
#3860000
0%
#3870000
b1 4
b100100 9
1%
#3880000
0%
#3890000
b10 4
b100101 9
1%
#3900000
0%
#3910000
b11 4
b100110 9
1%
#3920000
0%
#3930000
b0 4
b100111 9
1%
#3940000
0%
#3950000
b1 4
b101000 9
1%
#3960000
0%
#3970000
b10 4
b101001 9
1%
#3980000
0%
#3990000
b11 4
b101010 9
1%
#4000000
0%
#4010000
b0 4
b101011 9
1%
#4020000
0%
#4030000
b1 4
b101100 9
1%
#4040000
0%
#4050000
b10 4
b101101 9
1%
#4060000
0%
#4070000
b11 4
b101110 9
1%
#4080000
0%
#4090000
b0 4
b101111 9
1%
#4100000
0%
#4110000
b1 4
b110000 9
1%
#4120000
0%
#4130000
b10 4
b110001 9
1%
#4140000
0%
#4150000
b11 4
b110010 9
1%
#4160000
0%
#4170000
b11 3
b0 4
b0 9
1%
#4180000
0%
#4190000
b1 4
b1 9
1%
#4200000
0%
#4210000
b10 4
b10 9
1%
#4220000
0%
#4230000
b11 4
b11 9
1%
#4240000
0%
#4250000
b0 4
b100 9
1%
#4260000
0%
#4270000
b1 4
b101 9
1%
#4280000
0%
#4290000
b10 4
b110 9
1%
#4300000
0%
#4310000
b11 4
b111 9
1%
#4320000
0%
#4330000
b0 4
b1000 9
1%
#4340000
0%
#4350000
b1 4
b1001 9
1%
#4360000
0%
#4370000
b10 4
b1010 9
1%
#4380000
0%
#4390000
b11 4
b1011 9
1%
#4400000
0%
#4410000
b0 4
b1100 9
1%
#4420000
0%
#4430000
b1 4
b1101 9
1%
#4440000
0%
#4450000
b10 4
b1110 9
1%
#4460000
0%
#4470000
b11 4
b1111 9
1%
#4480000
0%
#4490000
b0 4
b10000 9
1%
#4500000
0%
#4510000
b1 4
b10001 9
1%
#4520000
0%
#4530000
b10 4
b10010 9
1%
#4540000
0%
#4550000
b11 4
b10011 9
1%
#4560000
0%
#4570000
b0 4
b10100 9
1%
#4580000
0%
#4590000
b1 4
b10101 9
1%
#4600000
0%
#4610000
b10 4
b10110 9
1%
#4620000
0%
#4630000
b11 4
b10111 9
1%
#4640000
0%
#4650000
b0 4
b11000 9
1%
#4660000
0%
#4670000
b1 4
b11001 9
1%
#4680000
0%
#4690000
b10 4
b11010 9
1%
#4700000
0%
#4710000
b11 4
b11011 9
1%
#4720000
0%
#4730000
b0 4
b11100 9
1%
#4740000
0%
#4750000
b1 4
b11101 9
1%
#4760000
0%
#4770000
b10 4
b11110 9
1%
#4780000
0%
#4790000
b11 4
b11111 9
1%
#4800000
0%
#4810000
b0 4
b100000 9
1%
#4820000
0%
#4830000
b1 4
b100001 9
1%
#4840000
0%
#4850000
b10 4
b100010 9
1%
#4860000
0%
#4870000
b11 4
b100011 9
1%
#4880000
0%
#4890000
b0 4
b100100 9
1%
#4900000
0%
#4910000
b1 4
b100101 9
1%
#4920000
0%
#4930000
b10 4
b100110 9
1%
#4940000
0%
#4950000
b11 4
b100111 9
1%
#4960000
0%
#4970000
b0 4
b101000 9
1%
#4980000
0%
#4990000
b1 4
b101001 9
1%
#5000000
0%
#5010000
b10 4
b101010 9
1%
#5020000
0%
#5030000
b11 4
b101011 9
1%
#5040000
0%
#5050000
b0 4
b101100 9
1%
#5060000
0%
#5070000
b1 4
b101101 9
1%
#5080000
0%
#5090000
b10 4
b101110 9
1%
#5100000
0%
#5110000
b11 4
b101111 9
1%
#5120000
0%
#5130000
b0 4
b110000 9
1%
#5140000
0%
#5150000
b1 4
b110001 9
1%
#5160000
0%
#5170000
b10 4
b110010 9
1%
#5180000
0%
#5190000
b100 3
b11 4
b0 9
1%
#5200000
0%
#5210000
b0 4
b1 9
1%
#5220000
0%
#5230000
b1 4
b10 9
1%
#5240000
0%
#5250000
b10 4
b11 9
1%
#5260000
0%
#5270000
b11 4
b100 9
1%
#5280000
0%
#5290000
b0 4
b101 9
1%
#5300000
0%
#5310000
b1 4
b110 9
1%
#5320000
0%
#5330000
b10 4
b111 9
1%
#5340000
0%
#5350000
b11 4
b1000 9
1%
#5360000
0%
#5370000
b0 4
b1001 9
1%
#5380000
0%
#5390000
b1 4
b1010 9
1%
#5400000
0%
#5410000
b10 4
b1011 9
1%
#5420000
0%
#5430000
b11 4
b1100 9
1%
#5440000
0%
#5450000
b0 4
b1101 9
1%
#5460000
0%
#5470000
b1 4
b1110 9
1%
#5480000
0%
#5490000
b10 4
b1111 9
1%
#5500000
0%
#5510000
b11 4
b10000 9
1%
#5520000
0%
#5530000
b0 4
b10001 9
1%
#5540000
0%
#5550000
b1 4
b10010 9
1%
#5560000
0%
#5570000
b10 4
b10011 9
1%
#5580000
0%
#5590000
b11 4
b10100 9
1%
#5600000
0%
#5610000
b0 4
b10101 9
1%
#5620000
0%
#5630000
b1 4
b10110 9
1%
#5640000
0%
#5650000
b10 4
b10111 9
1%
#5660000
0%
#5670000
b11 4
b11000 9
1%
#5680000
0%
#5690000
b0 4
b11001 9
1%
#5700000
0%
#5710000
b1 4
b11010 9
1%
#5720000
0%
#5730000
b10 4
b11011 9
1%
#5740000
0%
#5750000
b11 4
b11100 9
1%
#5760000
0%
#5770000
b0 4
b11101 9
1%
#5780000
0%
#5790000
b1 4
b11110 9
1%
#5800000
0%
#5810000
b10 4
b11111 9
1%
#5820000
0%
#5830000
b11 4
b100000 9
1%
#5840000
0%
#5850000
b0 4
b100001 9
1%
#5860000
0%
#5870000
b1 4
b100010 9
1%
#5880000
0%
#5890000
b10 4
b100011 9
1%
#5900000
0%
#5910000
b11 4
b100100 9
1%
#5920000
0%
#5930000
b0 4
b100101 9
1%
#5940000
0%
#5950000
b1 4
b100110 9
1%
#5960000
0%
#5970000
b10 4
b100111 9
1%
#5980000
0%
#5990000
b11 4
b101000 9
1%
#6000000
0%
#6010000
b0 4
b101001 9
1%
#6020000
0%
#6030000
b1 4
b101010 9
1%
#6040000
0%
#6050000
b10 4
b101011 9
1%
#6060000
0%
#6070000
b11 4
b101100 9
1%
#6080000
0%
#6090000
b0 4
b101101 9
1%
#6100000
0%
#6110000
b1 4
b101110 9
1%
#6120000
0%
#6130000
b10 4
b101111 9
1%
#6140000
0%
#6150000
b11 4
b110000 9
1%
#6160000
0%
#6170000
b0 4
b110001 9
1%
#6180000
0%
#6190000
b1 4
b110010 9
1%
#6200000
0%
#6210000
b101 3
b10 4
b0 9
1%
#6220000
0%
#6230000
b11 4
b1 9
1%
#6240000
0%
#6250000
b0 4
b10 9
1%
#6260000
0%
#6270000
b1 4
b11 9
1%
#6280000
0%
#6290000
b10 4
b100 9
1%
#6300000
0%
#6310000
b11 4
b101 9
1%
#6320000
0%
#6330000
b0 4
b110 9
1%
#6340000
0%
#6350000
b1 4
b111 9
1%
#6360000
0%
#6370000
b10 4
b1000 9
1%
#6380000
0%
#6390000
b11 4
b1001 9
1%
#6400000
0%
#6410000
b0 4
b1010 9
1%
#6420000
0%
#6430000
b1 4
b1011 9
1%
#6440000
0%
#6450000
b10 4
b1100 9
1%
#6460000
0%
#6470000
b11 4
b1101 9
1%
#6480000
0%
#6490000
b0 4
b1110 9
1%
#6500000
0%
#6510000
b1 4
b1111 9
1%
#6520000
0%
#6530000
b10 4
b10000 9
1%
#6540000
0%
#6550000
b11 4
b10001 9
1%
#6560000
0%
#6570000
b0 4
b10010 9
1%
#6580000
0%
#6590000
b1 4
b10011 9
1%
#6600000
0%
#6610000
b10 4
b10100 9
1%
#6620000
0%
#6630000
b11 4
b10101 9
1%
#6640000
0%
#6650000
b0 4
b10110 9
1%
#6660000
0%
#6670000
b1 4
b10111 9
1%
#6680000
0%
#6690000
b10 4
b11000 9
1%
#6700000
0%
#6710000
b11 4
b11001 9
1%
#6720000
0%
#6730000
b0 4
b11010 9
1%
#6740000
0%
#6750000
b1 4
b11011 9
1%
#6760000
0%
#6770000
b10 4
b11100 9
1%
#6780000
0%
#6790000
b11 4
b11101 9
1%
#6800000
0%
#6810000
b0 4
b11110 9
1%
#6820000
0%
#6830000
b1 4
b11111 9
1%
#6840000
0%
#6850000
b10 4
b100000 9
1%
#6860000
0%
#6870000
b11 4
b100001 9
1%
#6880000
0%
#6890000
b0 4
b100010 9
1%
#6900000
0%
#6910000
b1 4
b100011 9
1%
#6920000
0%
#6930000
b10 4
b100100 9
1%
#6940000
0%
#6950000
b11 4
b100101 9
1%
#6960000
0%
#6970000
b0 4
b100110 9
1%
#6980000
0%
#6990000
b1 4
b100111 9
1%
#7000000
0%
#7010000
b10 4
b101000 9
1%
#7020000
0%
#7030000
b11 4
b101001 9
1%
#7040000
0%
#7050000
b0 4
b101010 9
1%
#7060000
0%
