src/BCDtoSSeg.v
module BCDtoSSeg (
    input [3:0] BCD, 
    input [3:0] s,
    output reg [0:6] SSeg, 
    output [3:0] an
  );
  
  assign an = BCD;

  always @ ( * ) begin
    case (BCD)
      4'b0000: SSeg = 7'b0000001; // "0"  
  	  4'b0001: SSeg = 7'b1001111; // "1" 
  	  4'b0010: SSeg = 7'b0010010; // "2" 
  	  4'b0011: SSeg = 7'b0000110; // "3" 
  	  4'b0100: SSeg = 7'b1001100; // "4" 
  	  4'b0101: SSeg = 7'b0100100; // "5" 
  	  4'b0110: SSeg = 7'b0100000; // "6" 
  	  4'b0111: SSeg = 7'b0001111; // "7" 
  	  4'b1000: SSeg = 7'b0000000; // "8"  
  	  4'b1001: SSeg = 7'b0000100; // "9" 
      4'ha: SSeg = 7'b0001000;  
      4'hb: SSeg = 7'b1100000;
      4'hc: SSeg = 7'b0110001;
      4'hd: SSeg = 7'b1000010;
      4'he: SSeg = 7'b0110000;
      4'hf: SSeg = 7'b0111000;
       default: SSeg = 7'b0000000;
    endcase
  end

endmodule

src/BCD.v
module separar_num (
    input  [5:0] num,
    input clk2,
    output reg [3:0] BCD
);

parameter cont = 1;
reg algo = 0; // Alterna entre las cifras


always @ ( posedge clk2 ) begin
    case (algo)
    0: begin
        BCD <= num%10; algo = 1; // Se usa "<=" ya que es lógica secuencial
        end
    1: begin
        BCD <= (num- num % 10) / 10; algo=0;
        end
endcase
end
endmodule

src/caja.v
module caja (
    input [5:0] num,
    input clk2,
    input [3:0] s,
    output [0:6] SSeg,
    output [3:0] an
);

  wire [3:0] BCD;

  // Instancia de módulo que separa el número en dígitos
  separar_num suma (
    .num(num),
    .clk2(clk2),
    .BCD(BCD)
  );

  // Instancia del decodificador BCD a 7 segmentos
  BCDtoSSeg sumar (
    .BCD(BCD),
    .s(s),          // señal para multiplexación externa
    .SSeg(SSeg),
    .an(an)
  );

endmodule

src/sum1b_estruc.v
module sum1b_estruc (
    input A, 
    input B, 
    input Ci,
    output Cout,
    output S
  );
  // creo cables internos para conectar compuertas lógicas.
    wire a_ab; // compuerta and entre a y b
    wire x_ab; // compuerta xor entre a y b
    wire cout_t; 
  
    and(a_ab,A,B); // Esto es una compuerta AND entre A y B. Guarda el resultado en a_ab.
    xor(S,x_ab,Ci);
    xor(x_ab,A,B);
    and(cout_t,x_ab,Ci);
    or (Cout,cout_t,a_ab);
  
  endmodule

src/sum4b_estruc.v
 module sum4b_estruc (
  input  [3:0] A,
  input  [3:0] B,
  input        Ci,
  output [3:0] S,
  output       Cout
);

  wire c1, c2, c3;

  sum1b_estruc FA0 (
    .A   (A[0]),
    .B   (B[0]),
    .Ci  (Ci),
    .S   (S[0]),
    .Cout(c1)
  );

  sum1b_estruc FA1 (
    .A   (A[1]),
    .B   (B[1]),
    .Ci  (c1),
    .S   (S[1]),
    .Cout(c2)
  );

  sum1b_estruc FA2 (
    .A   (A[2]),
    .B   (B[2]),
    .Ci  (c2),
    .S   (S[2]),
    .Cout(c3)
  );

  sum1b_estruc FA3 (
    .A   (A[3]),
    .B   (B[3]),
    .Ci  (c3),
    .S   (S[3]),
    .Cout(Cout)
  );

endmodule

src/sumayresta_estruc.v
module sumayresta_estruc (
  input [3:0] A,
  input [3:0] B,
  input Sel,              // 0 = suma, 1 = resta
  output signed [3:0] S,
  output Cout
);

  wire [3:0] B_mod;       // B modificado según Sel
  
  wire [3:0] Sn;
  
  wire Coutn;

  // XOR para invertir B si Sel=1 (resta)
  assign B_mod[0] = B[0] ^ Sel;
  assign B_mod[1] = B[1] ^ Sel;
  assign B_mod[2] = B[2] ^ Sel;
  assign B_mod[3] = B[3] ^ Sel;

  // Instancia del sumador de 4 bits estructural
  sum4b_estruc suma (
    .A(A),
    .B(B_mod),
    .Ci(Sel),            // Sel = 0 suma directa, Sel = 1 hace B + 1 (complemento a 2)
    .S(Sn),
    .Cout(Coutn)
  );
  
  assign Cout = ~Coutn;
  assign S = ~ Sn;

endmodule

src/top_sumador_visual.v
module top_sumador_visual (
    input [3:0] A,
    input [3:0] B,
    input Sel,              // 0 = suma, 1 = resta
    input clk2,
    input [3:0] s,
    output [0:6] SSeg,
    output [3:0] an
);

  wire signed [3:0] S_raw;
  wire [5:0] num_abs;

  // Resultado de la operación suma/resta
  sumayresta_estruc alu (
    .A(A),
    .B(B),
    .Sel(Sel),
    .S(S_raw),
    .Cout()       // Puedes conectarlo si lo necesitas
  );

  // Convertir el resultado a número positivo (valor absoluto)
  assign num_abs = (S_raw < 0) ? -S_raw : S_raw;

  // Visualización del número (sin signo)
  caja display_unit (
    .num(num_abs),
    .clk2(clk2),
    .s(s),
    .SSeg(SSeg),
    .an(an)
  );

endmodule

src/top_sumador_visual_tb.v
`timescale 1ns/1ps

`include "src/top_sumador_visual.v"
`include "src/caja.v"
`include "src/BCDtoSSeg.v"
`include "src/BCD.v"
`include "src/sumayresta_estruc.v"
`include "src/sum4b_estruc.v"
`include "src/sum1b_estruc.v"


module top_sumador_visual_tb;

  // Entradas
  reg [3:0] A_tb;
  reg [3:0] B_tb;
  reg Sel_tb;
  reg clk2_tb;
  reg [3:0] s_tb;

  // Salidas
  wire [0:6] SSeg_tb;
  wire [3:0] an_tb;

  // Instancia del módulo superior
  top_sumador_visual uut (
    .A(A_tb),
    .B(B_tb),
    .Sel(Sel_tb),
    .clk2(clk2_tb),
    .s(s_tb),
    .SSeg(SSeg_tb),
    .an(an_tb)
  );

  // Generación del reloj: 10 ns de periodo
  always #5 clk2_tb = ~clk2_tb;

//   // Rueda de multiplexación de displays
//   initial begin
//     s_tb = 4'b1110;
//     forever #40 s_tb = {s_tb[2:0], s_tb[3]}; // Rota el display activo
//   end

  // Estímulos
  initial begin
    clk2_tb = 0;
    
    A_tb = 4'd7; B_tb = 4'd1; Sel_tb = 0; #100;  // 7 + 1 = 8
    A_tb = 4'd6; B_tb = 4'd4; Sel_tb = 0; #100;  // 6 + 4 = 10
    A_tb = 4'd5; B_tb = 4'd3; Sel_tb = 1; #100;  // 5 - 3 = 2
    A_tb = 4'd2; B_tb = 4'd5; Sel_tb = 1; #100;  // 2 - 5 = -3
    A_tb = 4'd0; B_tb = 4'd8; Sel_tb = 1; #100;  // 0 - 8 = -8
    A_tb = 4'd15; B_tb = 4'd1; Sel_tb = 0; #100; // 15 + 1 = 16

    $finish;
  end

  // Archivo de simulación para GTKWave
  initial begin
    $dumpfile("top_sumador_visual_tb.vcd");
    $dumpvars(-1, uut);
  end

endmodule

build/top_sumador_visual_tb.vcd
$date
	Mon Jun 30 09:27:38 2025
$end
$version
	Icarus Verilog
$end
$timescale
	1ps
$end
$scope module top_sumador_visual_tb $end
$scope module uut $end
$var wire 4 ! A [3:0] $end
$var wire 4 " B [3:0] $end
$var wire 1 # Sel $end
$var wire 1 $ clk2 $end
$var wire 4 % s [3:0] $end
$var wire 6 & num_abs [5:0] $end
$var wire 4 ' an [3:0] $end
$var wire 4 ( S_raw [3:0] $end
$var wire 7 ) SSeg [0:6] $end
$scope module alu $end
$var wire 4 * A [3:0] $end
$var wire 4 + B [3:0] $end
$var wire 1 , Cout $end
$var wire 4 - S [3:0] $end
$var wire 1 # Sel $end
$var wire 4 . Sn [3:0] $end
$var wire 1 / Coutn $end
$var wire 4 0 B_mod [3:0] $end
$scope module suma $end
$var wire 4 1 A [3:0] $end
$var wire 4 2 B [3:0] $end
$var wire 1 # Ci $end
$var wire 1 3 c3 $end
$var wire 1 4 c2 $end
$var wire 1 5 c1 $end
$var wire 4 6 S [3:0] $end
$var wire 1 / Cout $end
$scope module FA0 $end
$var wire 1 7 A $end
$var wire 1 8 B $end
$var wire 1 # Ci $end
$var wire 1 5 Cout $end
$var wire 1 9 S $end
$var wire 1 : a_ab $end
$var wire 1 ; cout_t $end
$var wire 1 < x_ab $end
$upscope $end
$scope module FA1 $end
$var wire 1 = A $end
$var wire 1 > B $end
$var wire 1 5 Ci $end
$var wire 1 4 Cout $end
$var wire 1 ? S $end
$var wire 1 @ a_ab $end
$var wire 1 A cout_t $end
$var wire 1 B x_ab $end
$upscope $end
$scope module FA2 $end
$var wire 1 C A $end
$var wire 1 D B $end
$var wire 1 4 Ci $end
$var wire 1 3 Cout $end
$var wire 1 E S $end
$var wire 1 F a_ab $end
$var wire 1 G cout_t $end
$var wire 1 H x_ab $end
$upscope $end
$scope module FA3 $end
$var wire 1 I A $end
$var wire 1 J B $end
$var wire 1 3 Ci $end
$var wire 1 / Cout $end
$var wire 1 K S $end
$var wire 1 L a_ab $end
$var wire 1 M cout_t $end
$var wire 1 N x_ab $end
$upscope $end
$upscope $end
$upscope $end
$scope module display_unit $end
$var wire 1 $ clk2 $end
$var wire 6 O num [5:0] $end
$var wire 4 P s [3:0] $end
$var wire 4 Q an [3:0] $end
$var wire 7 R SSeg [0:6] $end
$var wire 4 S BCD [3:0] $end
$scope module suma $end
$var wire 1 $ clk2 $end
$var wire 6 T num [5:0] $end
$var parameter 32 U cont $end
$var reg 4 V BCD [3:0] $end
$var reg 1 W algo $end
$upscope $end
$scope module sumar $end
$var wire 4 X BCD [3:0] $end
$var wire 4 Y an [3:0] $end
$var wire 4 Z s [3:0] $end
$var reg 7 [ SSeg [0:6] $end
$upscope $end
$upscope $end
$upscope $end
$upscope $end
$enddefinitions $end
$comment Show the parameter values. $end
$dumpall
b1 U
$end
#0
$dumpvars
bx [
bx Z
bx Y
bx X
0W
bx V
b111 T
bx S
bx R
bx Q
bx P
b111 O
0N
0M
0L
1K
0J
0I
1H
1G
0F
0E
0D
1C
1B
1A
0@
0?
0>
1=
0<
0;
1:
09
18
17
b1000 6
15
14
13
b1 2
b111 1
b1 0
0/
b1000 .
b111 -
1,
b1 +
b111 *
bx )
b111 (
bx '
b111 &
bx %
0$
0#
b1 "
b111 !
$end
#5000
b1111 )
b1111 R
b1111 [
b111 '
b111 Q
b111 Y
b111 S
b111 V
b111 X
1W
1$
#10000
0$
#15000
b1 )
b1 R
b1 [
b0 '
b0 Q
b0 Y
b0 S
b0 V
b0 X
0W
1$
#20000
0$
#25000
b1111 )
b1111 R
b1111 [
b111 '
b111 Q
b111 Y
b111 S
b111 V
b111 X
1W
1$
#30000
0$
#35000
b1 )
b1 R
b1 [
b0 '
b0 Q
b0 Y
b0 S
b0 V
b0 X
0W
1$
#40000
0$
#45000
b1111 )
b1111 R
b1111 [
b111 '
b111 Q
b111 Y
b111 S
b111 V
b111 X
1W
1$
#50000
0$
#55000
b1 )
b1 R
b1 [
b0 '
b0 Q
b0 Y
b0 S
b0 V
b0 X
0W
1$
#60000
0$
#65000
b1111 )
b1111 R
b1111 [
b111 '
b111 Q
b111 Y
b111 S
b111 V
b111 X
1W
1$
#70000
0$
#75000
b1 )
b1 R
b1 [
b0 '
b0 Q
b0 Y
b0 S
b0 V
b0 X
0W
1$
#80000
0$
#85000
b1111 )
b1111 R
b1111 [
b111 '
b111 Q
b111 Y
b111 S
b111 V
b111 X
1W
1$
#90000
0$
#95000
b1 )
b1 R
b1 [
b0 '
b0 Q
b0 Y
b0 S
b0 V
b0 X
0W
1$
#100000
0G
04
b101 &
b101 O
b101 T
1F
0H
1?
0A
b101 (
b101 -
08
1D
05
b1010 .
b1010 6
09
b100 0
b100 2
0:
0<
07
0$
b100 "
b100 +
b110 !
b110 *
b110 1
#105000
b100100 )
b100100 R
b100100 [
b101 '
b101 Q
b101 Y
b101 S
b101 V
b101 X
1W
1$
#110000
0$
#115000
b1 )
b1 R
b1 [
b0 '
b0 Q
b0 Y
b0 S
b0 V
b0 X
0W
1$
#120000
0$
#125000
b100100 )
b100100 R
b100100 [
b101 '
b101 Q
b101 Y
b101 S
b101 V
b101 X
1W
1$
#130000
0$
#135000
b1 )
b1 R
b1 [
b0 '
b0 Q
b0 Y
b0 S
b0 V
b0 X
0W
1$
#140000
0$
#145000
b100100 )
b100100 R
b100100 [
b101 '
b101 Q
b101 Y
b101 S
b101 V
b101 X
1W
1$
#150000
0$
#155000
b1 )
b1 R
b1 [
b0 '
b0 Q
b0 Y
b0 S
b0 V
b0 X
0W
1$
#160000
0$
#165000
b100100 )
b100100 R
b100100 [
b101 '
b101 Q
b101 Y
b101 S
b101 V
b101 X
1W
1$
#170000
0$
#175000
b1 )
b1 R
b1 [
b0 '
b0 Q
b0 Y
b0 S
b0 V
b0 X
0W
1$
#180000
0$
#185000
b100100 )
b100100 R
b100100 [
b101 '
b101 Q
b101 Y
b101 S
b101 V
b101 X
1W
1$
#190000
0$
#195000
b1 )
b1 R
b1 [
b0 '
b0 Q
b0 Y
b0 S
b0 V
b0 X
0W
1$
#200000
0,
1/
1M
0K
15
1N
b11 &
b11 O
b11 T
1;
1?
1J
b1101 (
b1101 -
1<
0B
b1100 0
b1100 2
b10 .
b10 6
09
17
0=
0$
1#
b11 "
b11 +
b101 !
b101 *
b101 1
#205000
b110 )
b110 R
b110 [
b11 '
b11 Q
b11 Y
b11 S
b11 V
b11 X
1W
1$
#210000
0$
#215000
b1 )
b1 R
b1 [
b0 '
b0 Q
b0 Y
b0 S
b0 V
b0 X
0W
1$
#220000
0$
#225000
b110 )
b110 R
b110 [
b11 '
b11 Q
b11 Y
b11 S
b11 V
b11 X
1W
1$
#230000
0$
#235000
b1 )
b1 R
b1 [
b0 '
b0 Q
b0 Y
b0 S
b0 V
b0 X
0W
1$
#240000
0$
#245000
b110 )
b110 R
b110 [
b11 '
b11 Q
b11 Y
b11 S
b11 V
b11 X
1W
1$
#250000
0$
#255000
b1 )
b1 R
b1 [
b0 '
b0 Q
b0 Y
b0 S
b0 V
b0 X
0W
1$
#260000
0$
#265000
b110 )
b110 R
b110 [
b11 '
b11 Q
b11 Y
b11 S
b11 V
b11 X
1W
1$
#270000
0$
#275000
b1 )
b1 R
b1 [
b0 '
b0 Q
b0 Y
b0 S
b0 V
b0 X
0W
1$
#280000
0$
#285000
b110 )
b110 R
b110 [
b11 '
b11 Q
b11 Y
b11 S
b11 V
b11 X
1W
1$
#290000
0$
#295000
b1 )
b1 R
b1 [
b0 '
b0 Q
b0 Y
b0 S
b0 V
b0 X
0W
1$
#300000
1,
0/
b10 &
b10 O
b10 T
1@
05
14
1K
0M
b10 (
b10 -
1>
0D
0;
19
0A
0?
03
b1101 .
b1101 6
1E
b1010 0
b1010 2
0<
0B
0F
0H
07
1=
0C
0$
b101 "
b101 +
b10 !
b10 *
b10 1
#305000
b10010 )
b10010 R
b10010 [
b10 '
b10 Q
b10 Y
b10 S
b10 V
b10 X
1W
1$
#310000
0$
#315000
b1 )
b1 R
b1 [
b0 '
b0 Q
b0 Y
b0 S
b0 V
b0 X
0W
1$
#320000
0$
#325000
b10010 )
b10010 R
b10010 [
b10 '
b10 Q
b10 Y
b10 S
b10 V
b10 X
1W
1$
#330000
0$
#335000
b1 )
b1 R
b1 [
b0 '
b0 Q
b0 Y
b0 S
b0 V
b0 X
0W
1$
#340000
0$
#345000
b10010 )
b10010 R
b10010 [
b10 '
b10 Q
b10 Y
b10 S
b10 V
b10 X
1W
1$
#350000
0$
#355000
b1 )
b1 R
b1 [
b0 '
b0 Q
b0 Y
b0 S
b0 V
b0 X
0W
1$
#360000
0$
#365000
b10010 )
b10010 R
b10010 [
b10 '
b10 Q
b10 Y
b10 S
b10 V
b10 X
1W
1$
#370000
0$
#375000
b1 )
b1 R
b1 [
b0 '
b0 Q
b0 Y
b0 S
b0 V
b0 X
0W
1$
#380000
0$
#385000
b10010 )
b10010 R
b10010 [
b10 '
b10 Q
b10 Y
b10 S
b10 V
b10 X
1W
1$
#390000
0$
#395000
b1 )
b1 R
b1 [
b0 '
b0 Q
b0 Y
b0 S
b0 V
b0 X
0W
1$
#400000
13
1G
1A
15
1;
09
1K
b111 &
b111 O
b111 T
1<
1H
0N
0E
b111 (
b111 -
18
1D
0J
14
b1000 .
b1000 6
0?
b111 0
b111 2
0@
1B
0=
0$
b1000 "
b1000 +
b0 !
b0 *
b0 1
#405000
b1111 )
b1111 R
b1111 [
b111 '
b111 Q
b111 Y
b111 S
b111 V
b111 X
1W
1$
#410000
0$
#415000
b1 )
b1 R
b1 [
b0 '
b0 Q
b0 Y
b0 S
b0 V
b0 X
0W
1$
#420000
0$
#425000
b1111 )
b1111 R
b1111 [
b111 '
b111 Q
b111 Y
b111 S
b111 V
b111 X
1W
1$
#430000
0$
#435000
b1 )
b1 R
b1 [
b0 '
b0 Q
b0 Y
b0 S
b0 V
b0 X
0W
1$
#440000
0$
#445000
b1111 )
b1111 R
b1111 [
b111 '
b111 Q
b111 Y
b111 S
b111 V
b111 X
1W
1$
#450000
0$
#455000
b1 )
b1 R
b1 [
b0 '
b0 Q
b0 Y
b0 S
b0 V
b0 X
0W
1$
#460000
0$
#465000
b1111 )
b1111 R
b1111 [
b111 '
b111 Q
b111 Y
b111 S
b111 V
b111 X
1W
1$
#470000
0$
#475000
b1 )
b1 R
b1 [
b0 '
b0 Q
b0 Y
b0 S
b0 V
b0 X
0W
1$
#480000
0$
#485000
b1111 )
b1111 R
b1111 [
b111 '
b111 Q
b111 Y
b111 S
b111 V
b111 X
1W
1$
#490000
0$
#495000
b1 )
b1 R
b1 [
b0 '
b0 Q
b0 Y
b0 S
b0 V
b0 X
0W
1$
#500000
0,
1/
b1 &
b1 O
b1 T
1A
0?
1G
0E
1M
0K
0>
0D
b1111 (
b1111 -
1:
0<
0@
1B
0F
1H
1N
b1 0
b1 2
b0 .
b0 6
09
0;
17
1=
1C
1I
0$
0#
b1 "
b1 +
b1111 !
b1111 *
b1111 1
#505000
b1001111 )
b1001111 R
b1001111 [
b1 '
b1 Q
b1 Y
b1 S
b1 V
b1 X
1W
1$
#510000
0$
#515000
b1 )
b1 R
b1 [
b0 '
b0 Q
b0 Y
b0 S
b0 V
b0 X
0W
1$
#520000
0$
#525000
b1001111 )
b1001111 R
b1001111 [
b1 '
b1 Q
b1 Y
b1 S
b1 V
b1 X
1W
1$
#530000
0$
#535000
b1 )
b1 R
b1 [
b0 '
b0 Q
b0 Y
b0 S
b0 V
b0 X
0W
1$
#540000
0$
#545000
b1001111 )
b1001111 R
b1001111 [
b1 '
b1 Q
b1 Y
b1 S
b1 V
b1 X
1W
1$
#550000
0$
#555000
b1 )
b1 R
b1 [
b0 '
b0 Q
b0 Y
b0 S
b0 V
b0 X
0W
1$
#560000
0$
#565000
b1001111 )
b1001111 R
b1001111 [
b1 '
b1 Q
b1 Y
b1 S
b1 V
b1 X
1W
1$
#570000
0$
#575000
b1 )
b1 R
b1 [
b0 '
b0 Q
b0 Y
b0 S
b0 V
b0 X
0W
1$
#580000
0$
#585000
b1001111 )
b1001111 R
b1001111 [
b1 '
b1 Q
b1 Y
b1 S
b1 V
b1 X
1W
1$
#590000
0$
#595000
b1 )
b1 R
b1 [
b0 '
b0 Q
b0 Y
b0 S
b0 V
b0 X
0W
1$
