src/BCDtoSSeg.v
module BCDtoSSeg (
  input [3:0] BCD,
  input [3:0] s,
  output reg [0:6] SSeg,
  output [3:0] an
);

  
  assign an = BCD;

  always @ ( * ) begin
    case (BCD)
      4'b0000: SSeg = 7'b0000001; // "0"  
  	  4'b0001: SSeg = 7'b1001111; // "1" 
  	  4'b0010: SSeg = 7'b0010010; // "2" 
  	  4'b0011: SSeg = 7'b0000110; // "3" 
  	  4'b0100: SSeg = 7'b1001100; // "4" 
  	  4'b0101: SSeg = 7'b0100100; // "5" 
  	  4'b0110: SSeg = 7'b0100000; // "6" 
  	  4'b0111: SSeg = 7'b0001111; // "7" 
  	  4'b1000: SSeg = 7'b0000000; // "8"  
  	  4'b1001: SSeg = 7'b0000100; // "9" 
      4'ha: SSeg = 7'b0001000;  
      4'hb: SSeg = 7'b1100000;
      4'hc: SSeg = 7'b0110001;
      4'hd: SSeg = 7'b1000010;
      4'he: SSeg = 7'b0110000;
      4'hf: SSeg = 7'b0111000;
       default: SSeg = 7'b0000000;
    endcase
  end

endmodule

src/BCD.v
module separar_num (
    input  [5:0] num,
    input clk2,
    output reg [3:0] BCD,
    output reg [3:0] sel
);

parameter cont = 1;
reg algo = 0; // Alterna entre las cifras


always @ ( posedge clk2 ) begin
    case (algo)
    0: begin
        BCD <= num%10; algo = 1; // Se usa "<=" ya que es lógica secuencial
        sel <= 4'b1110;
        end
    1: begin
        BCD <= (num- num % 10) / 10; algo=0;
        sel <= 4'b1101;
        end
endcase
end
endmodule

src/caja.v
module caja (
  input [5:0] num,
  input clk2,
  input [3:0] s,
  output [0:6] SSeg,
  output [3:0] an
);


  wire [3:0] BCD;

  // Instancia de módulo que separa el número en dígitos
  separar_num suma (
    .num(num),
    .clk2(clk2),
    .BCD(BCD),
    .sel(sel)
  );

  // Instancia del decodificador BCD a 7 segmentos
  BCDtoSSeg sumar (
    .BCD(BCD),
    .s(s),          // señal para multiplexación externa
    .SSeg(SSeg),
    .an(an)
  );

endmodule

src/clock_gen.v
module clock_gen (
  input clk,
  output reg clk2 = 0
);

  reg [15:0] count = 0;
  parameter DIV = 50000;

  always @(posedge clk) begin
    if (count >= DIV) begin
      count <= 0;
      clk2 <= ~clk2;
    end else begin
      count <= count + 1;
    end
  end

endmodule

src/sum1b_estruc.v
module sum1b_estruc (
    input A, 
    input B, 
    input Ci,
    output Cout,
    output S
  );
  // creo cables internos para conectar compuertas lógicas.
    wire a_ab; // compuerta and entre a y b
    wire x_ab; // compuerta xor entre a y b
    wire cout_t; 
  
    and(a_ab,A,B); // Esto es una compuerta AND entre A y B. Guarda el resultado en a_ab.
    xor(S,x_ab,Ci);
    xor(x_ab,A,B);
    and(cout_t,x_ab,Ci);
    or (Cout,cout_t,a_ab);
  
  endmodule

src/sum4b_estruc.v
 module sum4b_estruc (
  input  [3:0] A,
  input  [3:0] B,
  input        Ci,
  output [3:0] S,
  output       Cout
);

  wire c1, c2, c3;

  sum1b_estruc FA0 (
    .A   (A[0]),
    .B   (B[0]),
    .Ci  (Ci),
    .S   (S[0]),
    .Cout(c1)
  );

  sum1b_estruc FA1 (
    .A   (A[1]),
    .B   (B[1]),
    .Ci  (c1),
    .S   (S[1]),
    .Cout(c2)
  );

  sum1b_estruc FA2 (
    .A   (A[2]),
    .B   (B[2]),
    .Ci  (c2),
    .S   (S[2]),
    .Cout(c3)
  );

  sum1b_estruc FA3 (
    .A   (A[3]),
    .B   (B[3]),
    .Ci  (c3),
    .S   (S[3]),
    .Cout(Cout)
  );

endmodule

src/sumayresta_estruc.v
module sumayresta_estruc (
  input [3:0] A,
  input [3:0] B,
  input Sel,              // 0 = suma, 1 = resta
  output signed [3:0] S,
  output Cout
);

  wire [3:0] B_mod;       // B modificado según Sel
  
  wire [3:0] Sn;
  
  wire Coutn;

  // XOR para invertir B si Sel=1 (resta)
  assign B_mod[0] = B[0] ^ Sel;
  assign B_mod[1] = B[1] ^ Sel;
  assign B_mod[2] = B[2] ^ Sel;
  assign B_mod[3] = B[3] ^ Sel;

  // Instancia del sumador de 4 bits estructural
  sum4b_estruc suma (
    .A(A),
    .B(B_mod),
    .Ci(Sel),            // Sel = 0 suma directa, Sel = 1 hace B + 1 (complemento a 2)
    .S(Sn),
    .Cout(Coutn)
  );
  
  assign Cout = ~Coutn;
  assign S = ~ Sn;

endmodule

src/top_sumador_visual.v
module top_sumador_visual (
    input [3:0] A,
    input [3:0] B,
    input Sel,              // 0 = suma, 1 = resta
    input clk,
    input [3:0] s,
    output [0:6] SSeg,
    output [3:0] an
);

  wire signed [3:0] S_raw;
  wire [5:0] num_abs;

  wire clk2;

  // Resultado de la operación suma/resta
  sumayresta_estruc alu (
    .A(A),
    .B(B),
    .Sel(Sel),
    .S(S_raw),
    .Cout(Cout)      
  );

  clock_gen div (
    .clk(clk),
    .clk2(clk2)
  );

  // Convertir el resultado a número positivo (valor absoluto)

  // Visualización del número (sin signo)
  caja display_unit (
    .num(S_raw),
    .clk2(clk2),
    .s(s),
    .SSeg(SSeg),
    .an(an)
  );

endmodule

src/top_sumador_visual_tb.v
`timescale 1ns/1ps

`include "src/top_sumador_visual.v"
`include "src/caja.v"
`include "src/BCD.v"
`include "src/BCDtoSSeg.v"
`include "src/sumayresta_estruc.v"
`include "src/sum4b_estruc.v"
`include "src/sum1b_estruc.v"
`include "src/clock_gen.v"

module top_sumador_visual_tb;

  // Entradas
  reg [3:0] A_tb;
  reg [3:0] B_tb;
  reg Sel_tb;
  reg clk_tb;
  reg [3:0] s_tb;

  // Salidas
  wire [0:6] SSeg_tb;
  wire [3:0] an_tb;

  // Instancia del módulo superior
  top_sumador_visual uut (
    .A(A_tb),
    .B(B_tb),
    .Sel(Sel_tb),
    .clk(clk_tb),       // ahora clk_tb es la entrada principal
    .s(s_tb),
    .SSeg(SSeg_tb),
    .an(an_tb)
  );

  // Reloj principal (simula 100 MHz)
  always #5 clk_tb = ~clk_tb;

  // Secuencia de activación de displays
  initial begin
    s_tb = 4'b1110;
    forever #40 s_tb = {s_tb[2:0], s_tb[3]};
  end

  // Estímulos
  initial begin
    clk_tb = 0;

    A_tb = 4'd7;  B_tb = 4'd1;  Sel_tb = 0; #200; // 7 + 1 = 8
    A_tb = 4'd6;  B_tb = 4'd4;  Sel_tb = 0; #200; // 6 + 4 = 10
    A_tb = 4'd5;  B_tb = 4'd3;  Sel_tb = 1; #200; // 5 - 3 = 2
    A_tb = 4'd2;  B_tb = 4'd5;  Sel_tb = 1; #200; // 2 - 5 = -3
    A_tb = 4'd0;  B_tb = 4'd8;  Sel_tb = 1; #200; // 0 - 8 = -8
    A_tb = 4'd15; B_tb = 4'd1;  Sel_tb = 0; #200; // 15 + 1 = 16

    $finish;
  end

  // Archivo para GTKWave
  initial begin
    $dumpfile("top_sumador_visual_tb.vcd");
    $dumpvars(-1, uut);
  end

endmodule

build/top_sumador_visual_tb.vcd
$date
	Sat Jul  5 17:30:20 2025
$end
$version
	Icarus Verilog
$end
$timescale
	1ps
$end
$scope module top_sumador_visual_tb $end
$scope module uut $end
$var wire 4 ! A [3:0] $end
$var wire 4 " B [3:0] $end
$var wire 1 # Sel $end
$var wire 1 $ clk $end
$var wire 4 % s [3:0] $end
$var wire 1 & clk2 $end
$var wire 4 ' an [3:0] $end
$var wire 4 ( S_raw [3:0] $end
$var wire 7 ) SSeg [0:6] $end
$var wire 1 * Cout $end
$scope module alu $end
$var wire 4 + A [3:0] $end
$var wire 4 , B [3:0] $end
$var wire 1 * Cout $end
$var wire 4 - S [3:0] $end
$var wire 1 # Sel $end
$var wire 4 . Sn [3:0] $end
$var wire 1 / Coutn $end
$var wire 4 0 B_mod [3:0] $end
$scope module suma $end
$var wire 4 1 A [3:0] $end
$var wire 4 2 B [3:0] $end
$var wire 1 # Ci $end
$var wire 1 3 c3 $end
$var wire 1 4 c2 $end
$var wire 1 5 c1 $end
$var wire 4 6 S [3:0] $end
$var wire 1 / Cout $end
$scope module FA0 $end
$var wire 1 7 A $end
$var wire 1 8 B $end
$var wire 1 # Ci $end
$var wire 1 5 Cout $end
$var wire 1 9 S $end
$var wire 1 : a_ab $end
$var wire 1 ; cout_t $end
$var wire 1 < x_ab $end
$upscope $end
$scope module FA1 $end
$var wire 1 = A $end
$var wire 1 > B $end
$var wire 1 5 Ci $end
$var wire 1 4 Cout $end
$var wire 1 ? S $end
$var wire 1 @ a_ab $end
$var wire 1 A cout_t $end
$var wire 1 B x_ab $end
$upscope $end
$scope module FA2 $end
$var wire 1 C A $end
$var wire 1 D B $end
$var wire 1 4 Ci $end
$var wire 1 3 Cout $end
$var wire 1 E S $end
$var wire 1 F a_ab $end
$var wire 1 G cout_t $end
$var wire 1 H x_ab $end
$upscope $end
$scope module FA3 $end
$var wire 1 I A $end
$var wire 1 J B $end
$var wire 1 3 Ci $end
$var wire 1 / Cout $end
$var wire 1 K S $end
$var wire 1 L a_ab $end
$var wire 1 M cout_t $end
$var wire 1 N x_ab $end
$upscope $end
$upscope $end
$upscope $end
$scope module display_unit $end
$var wire 6 O num [5:0] $end
$var wire 4 P s [3:0] $end
$var wire 1 Q sel $end
$var wire 1 & clk2 $end
$var wire 4 R an [3:0] $end
$var wire 7 S SSeg [0:6] $end
$var wire 4 T BCD [3:0] $end
$scope module suma $end
$var wire 6 U num [5:0] $end
$var wire 1 & clk2 $end
$var parameter 32 V cont $end
$var reg 4 W BCD [3:0] $end
$var reg 1 X algo $end
$var reg 4 Y sel [3:0] $end
$upscope $end
$scope module sumar $end
$var wire 4 Z BCD [3:0] $end
$var wire 4 [ an [3:0] $end
$var wire 4 \ s [3:0] $end
$var reg 7 ] SSeg [0:6] $end
$upscope $end
$upscope $end
$scope module div $end
$var wire 1 $ clk $end
$var parameter 32 ^ DIV $end
$var reg 1 & clk2 $end
$var reg 16 _ count [15:0] $end
$upscope $end
$upscope $end
$upscope $end
$enddefinitions $end
$comment Show the parameter values. $end
$dumpall
b1100001101010000 ^
b1 V
$end
#0
$dumpvars
b0 _
bx ]
b1110 \
bx [
bx Z
bx Y
0X
bx W
b111 U
bx T
bx S
bx R
xQ
b1110 P
b111 O
0N
0M
0L
1K
0J
0I
1H
1G
0F
0E
0D
1C
1B
1A
0@
0?
0>
1=
0<
0;
1:
09
18
17
b1000 6
15
14
13
b1 2
b111 1
b1 0
0/
b1000 .
b111 -
b1 ,
b111 +
1*
bx )
b111 (
bx '
0&
b1110 %
0$
0#
b1 "
b111 !
$end
#5000
b1 _
1$
#10000
0$
#15000
b10 _
1$
#20000
0$
#25000
b11 _
1$
#30000
0$
#35000
b100 _
1$
#40000
0$
b1101 %
b1101 P
b1101 \
#45000
b101 _
1$
#50000
0$
#55000
b110 _
1$
#60000
0$
#65000
b111 _
1$
#70000
0$
#75000
b1000 _
1$
#80000
0$
b1011 %
b1011 P
b1011 \
#85000
b1001 _
1$
#90000
0$
#95000
b1010 _
1$
#100000
0$
#105000
b1011 _
1$
#110000
0$
#115000
b1100 _
1$
#120000
0$
b111 %
b111 P
b111 \
#125000
b1101 _
1$
#130000
0$
#135000
b1110 _
1$
#140000
0$
#145000
b1111 _
1$
#150000
0$
#155000
b10000 _
1$
#160000
0$
b1110 %
b1110 P
b1110 \
#165000
b10001 _
1$
#170000
0$
#175000
b10010 _
1$
#180000
0$
#185000
b10011 _
1$
#190000
0$
#195000
b10100 _
1$
#200000
0G
04
1F
0H
1?
0A
b101 O
b101 U
b101 (
b101 -
08
1D
05
b1010 .
b1010 6
09
b100 0
b100 2
0:
0<
07
0$
b1101 %
b1101 P
b1101 \
b100 "
b100 ,
b110 !
b110 +
b110 1
#205000
b10101 _
1$
#210000
0$
#215000
b10110 _
1$
#220000
0$
#225000
b10111 _
1$
#230000
0$
#235000
b11000 _
1$
#240000
0$
b1011 %
b1011 P
b1011 \
#245000
b11001 _
1$
#250000
0$
#255000
b11010 _
1$
#260000
0$
#265000
b11011 _
1$
#270000
0$
#275000
b11100 _
1$
#280000
0$
b111 %
b111 P
b111 \
#285000
b11101 _
1$
#290000
0$
#295000
b11110 _
1$
#300000
0$
#305000
b11111 _
1$
#310000
0$
#315000
b100000 _
1$
#320000
0$
b1110 %
b1110 P
b1110 \
#325000
b100001 _
1$
#330000
0$
#335000
b100010 _
1$
#340000
0$
#345000
b100011 _
1$
#350000
0$
#355000
b100100 _
1$
#360000
0$
b1101 %
b1101 P
b1101 \
#365000
b100101 _
1$
#370000
0$
#375000
b100110 _
1$
#380000
0$
#385000
b100111 _
1$
#390000
0$
#395000
b101000 _
1$
#400000
0*
1/
1M
0K
15
1N
1;
1?
1J
b111101 O
b111101 U
b1101 (
b1101 -
1<
0B
b1100 0
b1100 2
b10 .
b10 6
09
17
0=
0$
b1011 %
b1011 P
b1011 \
1#
b11 "
b11 ,
b101 !
b101 +
b101 1
#405000
b101001 _
1$
#410000
0$
#415000
b101010 _
1$
#420000
0$
#425000
b101011 _
1$
#430000
0$
#435000
b101100 _
1$
#440000
0$
b111 %
b111 P
b111 \
#445000
b101101 _
1$
#450000
0$
#455000
b101110 _
1$
#460000
0$
#465000
b101111 _
1$
#470000
0$
#475000
b110000 _
1$
#480000
0$
b1110 %
b1110 P
b1110 \
#485000
b110001 _
1$
#490000
0$
#495000
b110010 _
1$
#500000
0$
#505000
b110011 _
1$
#510000
0$
#515000
b110100 _
1$
#520000
0$
b1101 %
b1101 P
b1101 \
#525000
b110101 _
1$
#530000
0$
#535000
b110110 _
1$
#540000
0$
#545000
b110111 _
1$
#550000
0$
#555000
b111000 _
1$
#560000
0$
b1011 %
b1011 P
b1011 \
#565000
b111001 _
1$
#570000
0$
#575000
b111010 _
1$
#580000
0$
#585000
b111011 _
1$
#590000
0$
#595000
b111100 _
1$
#600000
1*
0/
1@
05
14
1K
0M
b10 O
b10 U
b10 (
b10 -
1>
0D
0;
19
0A
0?
03
b1101 .
b1101 6
1E
b1010 0
b1010 2
0<
0B
0F
0H
07
1=
0C
0$
b111 %
b111 P
b111 \
b101 "
b101 ,
b10 !
b10 +
b10 1
#605000
b111101 _
1$
#610000
0$
#615000
b111110 _
1$
#620000
0$
#625000
b111111 _
1$
#630000
0$
#635000
b1000000 _
1$
#640000
0$
b1110 %
b1110 P
b1110 \
#645000
b1000001 _
1$
#650000
0$
#655000
b1000010 _
1$
#660000
0$
#665000
b1000011 _
1$
#670000
0$
#675000
b1000100 _
1$
#680000
0$
b1101 %
b1101 P
b1101 \
#685000
b1000101 _
1$
#690000
0$
#695000
b1000110 _
1$
#700000
0$
#705000
b1000111 _
1$
#710000
0$
#715000
b1001000 _
1$
#720000
0$
b1011 %
b1011 P
b1011 \
#725000
b1001001 _
1$
#730000
0$
#735000
b1001010 _
1$
#740000
0$
#745000
b1001011 _
1$
#750000
0$
#755000
b1001100 _
1$
#760000
0$
b111 %
b111 P
b111 \
#765000
b1001101 _
1$
#770000
0$
#775000
b1001110 _
1$
#780000
0$
#785000
b1001111 _
1$
#790000
0$
#795000
b1010000 _
1$
#800000
13
1G
1A
15
1;
09
1K
1<
1H
0N
0E
b111 O
b111 U
b111 (
b111 -
18
1D
0J
14
b1000 .
b1000 6
0?
b111 0
b111 2
0@
1B
0=
0$
b1110 %
b1110 P
b1110 \
b1000 "
b1000 ,
b0 !
b0 +
b0 1
#805000
b1010001 _
1$
#810000
0$
#815000
b1010010 _
1$
#820000
0$
#825000
b1010011 _
1$
#830000
0$
#835000
b1010100 _
1$
#840000
0$
b1101 %
b1101 P
b1101 \
#845000
b1010101 _
1$
#850000
0$
#855000
b1010110 _
1$
#860000
0$
#865000
b1010111 _
1$
#870000
0$
#875000
b1011000 _
1$
#880000
0$
b1011 %
b1011 P
b1011 \
#885000
b1011001 _
1$
#890000
0$
#895000
b1011010 _
1$
#900000
0$
#905000
b1011011 _
1$
#910000
0$
#915000
b1011100 _
1$
#920000
0$
b111 %
b111 P
b111 \
#925000
b1011101 _
1$
#930000
0$
#935000
b1011110 _
1$
#940000
0$
#945000
b1011111 _
1$
#950000
0$
#955000
b1100000 _
1$
#960000
0$
b1110 %
b1110 P
b1110 \
#965000
b1100001 _
1$
#970000
0$
#975000
b1100010 _
1$
#980000
0$
#985000
b1100011 _
1$
#990000
0$
#995000
b1100100 _
1$
#1000000
0*
1/
1A
0?
1G
0E
1M
0K
0>
0D
b111111 O
b111111 U
b1111 (
b1111 -
1:
0<
0@
1B
0F
1H
1N
b1 0
b1 2
b0 .
b0 6
09
0;
17
1=
1C
1I
0$
b1101 %
b1101 P
b1101 \
0#
b1 "
b1 ,
b1111 !
b1111 +
b1111 1
#1005000
b1100101 _
1$
#1010000
0$
#1015000
b1100110 _
1$
#1020000
0$
#1025000
b1100111 _
1$
#1030000
0$
#1035000
b1101000 _
1$
#1040000
0$
b1011 %
b1011 P
b1011 \
#1045000
b1101001 _
1$
#1050000
0$
#1055000
b1101010 _
1$
#1060000
0$
#1065000
b1101011 _
1$
#1070000
0$
#1075000
b1101100 _
1$
#1080000
0$
b111 %
b111 P
b111 \
#1085000
b1101101 _
1$
#1090000
0$
#1095000
b1101110 _
1$
#1100000
0$
#1105000
b1101111 _
1$
#1110000
0$
#1115000
b1110000 _
1$
#1120000
0$
b1110 %
b1110 P
b1110 \
#1125000
b1110001 _
1$
#1130000
0$
#1135000
b1110010 _
1$
#1140000
0$
#1145000
b1110011 _
1$
#1150000
0$
#1155000
b1110100 _
1$
#1160000
0$
b1101 %
b1101 P
b1101 \
#1165000
b1110101 _
1$
#1170000
0$
#1175000
b1110110 _
1$
#1180000
0$
#1185000
b1110111 _
1$
#1190000
0$
#1195000
b1111000 _
1$
#1200000
0$
b1011 %
b1011 P
b1011 \
